ufo2ft/__init__.py
ufo2ft/constants.py
ufo2ft/errors.py
ufo2ft/featureCompiler.py
ufo2ft/fontInfoData.py
ufo2ft/infoCompiler.py
ufo2ft/instantiator.py
ufo2ft/instructionCompiler.py
ufo2ft/maxContextCalc.py
ufo2ft/outlineCompiler.py
ufo2ft/postProcessor.py
ufo2ft/preProcessor.py
ufo2ft/util.py
ufo2ft/_compilers/__init__.py
ufo2ft/_compilers/baseCompiler.py
ufo2ft/_compilers/interpolatableOTFCompiler.py
ufo2ft/_compilers/interpolatableTTFCompiler.py
ufo2ft/_compilers/otfCompiler.py
ufo2ft/_compilers/ttfCompiler.py
ufo2ft/_compilers/variableCFF2sCompiler.py
ufo2ft/_compilers/variableTTFsCompiler.py
ufo2ft/featureWriters/__init__.py
ufo2ft/featureWriters/__main__.py
ufo2ft/featureWriters/ast.py
ufo2ft/featureWriters/baseFeatureWriter.py
ufo2ft/featureWriters/cursFeatureWriter.py
ufo2ft/featureWriters/gdefFeatureWriter.py
ufo2ft/featureWriters/kernFeatureWriter.py
ufo2ft/featureWriters/kernFeatureWriter2.py
ufo2ft/featureWriters/markFeatureWriter.py
ufo2ft/filters/__init__.py
ufo2ft/filters/__main__.py
ufo2ft/filters/base.py
ufo2ft/filters/cubicToQuadratic.py
ufo2ft/filters/decomposeComponents.py
ufo2ft/filters/decomposeTransformedComponents.py
ufo2ft/filters/dottedCircle.py
ufo2ft/filters/dottedCircleFilter.py
ufo2ft/filters/explodeColorLayerGlyphs.py
ufo2ft/filters/flattenComponents.py
ufo2ft/filters/propagateAnchors.py
ufo2ft/filters/removeOverlaps.py
ufo2ft/filters/reverseContourDirection.py
ufo2ft/filters/skipExportGlyphs.py
ufo2ft/filters/sortContours.py
ufo2ft/filters/transformations.py
ufo2ft-3.7.0.dist-info/licenses/LICENSE
ufo2ft-3.7.0.dist-info/METADATA
ufo2ft-3.7.0.dist-info/WHEEL
ufo2ft-3.7.0.dist-info/top_level.txt
ufo2ft-3.7.0.dist-info/RECORD
