Metadata-Version: 2.4
Name: ufo2ft
Version: 3.7.0
Summary: A bridge between UFOs and FontTools.
Author: James Godfrey-Kittle
Author-email: Tal Leming <tal@typesupply.com>
Maintainer-email: Cosimo Lupo <cosimo@anthrotype.com>
License-Expression: MIT
Project-URL: Homepage, https://github.com/googlefonts/ufo2ft
Classifier: Development Status :: 5 - Production/Stable
Classifier: Environment :: Console
Classifier: Environment :: Other Environment
Classifier: Intended Audience :: Developers
Classifier: Intended Audience :: End Users/Desktop
Classifier: Natural Language :: English
Classifier: Operating System :: OS Independent
Classifier: Programming Language :: Python
Classifier: Programming Language :: Python :: 3
Classifier: Programming Language :: Python :: 3.10
Classifier: Programming Language :: Python :: 3.11
Classifier: Programming Language :: Python :: 3.12
Classifier: Programming Language :: Python :: 3.13
Classifier: Programming Language :: Python :: 3.14
Classifier: Topic :: Multimedia :: Graphics
Classifier: Topic :: Multimedia :: Graphics :: Editors :: Vector-Based
Classifier: Topic :: Multimedia :: Graphics :: Graphics Conversion
Classifier: Topic :: Software Development :: Libraries :: Python Modules
Requires-Python: >=3.10
License-File: LICENSE
Requires-Dist: booleanoperations>=0.9.0
Requires-Dist: cffsubr>=0.3.0
Requires-Dist: fontmath>=0.9.4
Requires-Dist: fonttools[ufo]>=4.61.1
Provides-Extra: compreffor
Requires-Dist: compreffor>=0.5.6; extra == "compreffor"
Provides-Extra: cffsubr
Provides-Extra: dev
Requires-Dist: black; extra == "dev"
Requires-Dist: coverage; extra == "dev"
Requires-Dist: flake8-bugbear; extra == "dev"
Requires-Dist: isort; extra == "dev"
Requires-Dist: pytest; extra == "dev"
Requires-Dist: syrupy; extra == "dev"
Provides-Extra: pathops
Requires-Dist: skia-pathops>=0.8.0; extra == "pathops"
Provides-Extra: test
Requires-Dist: pytest; extra == "test"
Requires-Dist: syrupy; extra == "test"
Dynamic: license-file
